CHANGES.txt
MANIFEST
MANIFEST.in
README.txt
setup.py
ZenPacks/__init__.py
ZenPacks.lbn.ZopeMonitor.egg-info/PKG-INFO
ZenPacks.lbn.ZopeMonitor.egg-info/SOURCES.txt
ZenPacks.lbn.ZopeMonitor.egg-info/dependency_links.txt
ZenPacks.lbn.ZopeMonitor.egg-info/entry_points.txt
ZenPacks.lbn.ZopeMonitor.egg-info/namespace_packages.txt
ZenPacks.lbn.ZopeMonitor.egg-info/not-zip-safe
ZenPacks.lbn.ZopeMonitor.egg-info/requires.txt
ZenPacks.lbn.ZopeMonitor.egg-info/top_level.txt
ZenPacks/lbn/__init__.py
ZenPacks/lbn/ZopeMonitor/__init__.py
ZenPacks/lbn/ZopeMonitor/config.py
ZenPacks/lbn/ZopeMonitor/configure.zcml
ZenPacks/lbn/ZopeMonitor/info.py
ZenPacks/lbn/ZopeMonitor/interfaces.py
ZenPacks/lbn/ZopeMonitor/setuphandlers.py
ZenPacks/lbn/ZopeMonitor/datasources/DataSourceBase.py
ZenPacks/lbn/ZopeMonitor/datasources/ZopeCacheDataSource.py
ZenPacks/lbn/ZopeMonitor/datasources/ZopeDBActivityDataSource.py
ZenPacks/lbn/ZopeMonitor/datasources/ZopeMemoryDataSource.py
ZenPacks/lbn/ZopeMonitor/datasources/ZopeThreadsDataSource.py
ZenPacks/lbn/ZopeMonitor/datasources/__init__.py
ZenPacks/lbn/ZopeMonitor/parsers/Munin.py
ZenPacks/lbn/ZopeMonitor/parsers/__init__.py
ZenPacks/lbn/ZopeMonitor/skins/ZenPacks.lbn.ZopeMonitor/editZopeMonitorDataSource.pt
ZenPacks/lbn/ZopeMonitor/tests/__init__.py
ZenPacks/lbn/ZopeMonitor/tests/testMuninParser.py
ZenPacks/lbn/ZopeMonitor/tests/testZopeMonitor.py