Metadata-Version: 1.0
Name: ZenPacks.lbn.ZopeMonitor
Version: 4.0.2
Summary: ZenPack to monitor Zope Application Server stats
Home-page: http://linux.last-bastion.net/LBN/up2date/monitor
Author: Last Bastion Network
Author-email: helpdesk@last-bastion.net
License: ZPL/2.1
Platform: UNKNOWN
Classifier: Framework :: Zope2
Classifier: Framework :: Plone
Classifier: Intended Audience :: Information Technology
Classifier: Programming Language :: Python
Classifier: Programming Language :: Zope
Classifier: Development Status :: 5 - Production/Stable
Classifier: License :: OSI Approved :: Zope Public License
Classifier: Topic :: System :: Monitoring
Classifier: Topic :: System :: Networking :: Monitoring
